LICENSE
README.md
setup.cfg
setup.py
GoogleTTS/__init__.py
GoogleTTS/google_tts.py
GoogleTTS/utils.py
GoogleTTS/version.py
google_tts.egg-info/PKG-INFO
google_tts.egg-info/SOURCES.txt
google_tts.egg-info/dependency_links.txt
google_tts.egg-info/requires.txt
google_tts.egg-info/top_level.txt