Metadata-Version: 2.1
Name: google-tts
Version: 1.0.1
Summary: google-tts (Google Text-to-Speech), a Python library with Google text-to-speech API
Home-page: https://github.com/ykutaykuta/google-tts
Author: ykuta
Author-email: ykutaykuta@gmail.com
License: MIT
Keywords: google-tts,text to speech,google
Platform: UNKNOWN
Classifier: License :: OSI Approved :: MIT License
Classifier: Operating System :: MacOS
Classifier: Operating System :: Unix
Classifier: Operating System :: POSIX
Classifier: Operating System :: POSIX :: Linux
Classifier: Operating System :: Microsoft :: Windows
Classifier: Programming Language :: Python :: 3.6
Classifier: Programming Language :: Python :: 3.7
Classifier: Programming Language :: Python :: 3.8
Classifier: Programming Language :: Python :: 3.9
Classifier: Topic :: Software Development :: Libraries
Classifier: Topic :: Multimedia :: Sound/Audio :: Speech
Requires-Python: >=3.6
